{
  "openapi": "3.0.1",
  "info": {
    "title": "F1Project",
    "version": "1.0"
  },
  "paths": {
    "/api/F1driver": {
      "get": {
        "tags": [
          "F1driver"
        ],
        "responses": {
          "200": {
            "description": "OK",
            "content": {
              "text/plain": {
                "schema": {
                  "type": "array",
                  "items": {
                    "$ref": "#/components/schemas/F1driver"
                  }
                }
              },
              "application/json": {
                "schema": {
                  "type": "array",
                  "items": {
                    "$ref": "#/components/schemas/F1driver"
                  }
                }
              },
              "text/json": {
                "schema": {
                  "type": "array",
                  "items": {
                    "$ref": "#/components/schemas/F1driver"
                  }
                }
              }
            }
          }
        }
      },
      "post": {
        "tags": [
          "F1driver"
        ],
        "requestBody": {
          "content": {
            "application/json": {
              "schema": {
                "$ref": "#/components/schemas/F1driverDTO"
              }
            },
            "text/json": {
              "schema": {
                "$ref": "#/components/schemas/F1driverDTO"
              }
            },
            "application/*+json": {
              "schema": {
                "$ref": "#/components/schemas/F1driverDTO"
              }
            }
          }
        },
        "responses": {
          "200": {
            "description": "OK",
            "content": {
              "text/plain": {
                "schema": {
                  "$ref": "#/components/schemas/F1driver"
                }
              },
              "application/json": {
                "schema": {
                  "$ref": "#/components/schemas/F1driver"
                }
              },
              "text/json": {
                "schema": {
                  "$ref": "#/components/schemas/F1driver"
                }
              }
            }
          }
        }
      }
    },
    "/api/F1driver/Search_by_DriverId/{id}": {
      "get": {
        "tags": [
          "F1driver"
        ],
        "parameters": [
          {
            "name": "id",
            "in": "path",
            "required": true,
            "schema": {
              "type": "integer",
              "format": "int32"
            }
          }
        ],
        "responses": {
          "200": {
            "description": "OK",
            "content": {
              "text/plain": {
                "schema": {
                  "$ref": "#/components/schemas/F1driver"
                }
              },
              "application/json": {
                "schema": {
                  "$ref": "#/components/schemas/F1driver"
                }
              },
              "text/json": {
                "schema": {
                  "$ref": "#/components/schemas/F1driver"
                }
              }
            }
          }
        }
      }
    },
    "/api/F1driver/Search_by_DriverName/{name}": {
      "get": {
        "tags": [
          "F1driver"
        ],
        "parameters": [
          {
            "name": "name",
            "in": "path",
            "required": true,
            "schema": {
              "type": "string"
            }
          }
        ],
        "responses": {
          "200": {
            "description": "OK",
            "content": {
              "text/plain": {
                "schema": {
                  "$ref": "#/components/schemas/F1driver"
                }
              },
              "application/json": {
                "schema": {
                  "$ref": "#/components/schemas/F1driver"
                }
              },
              "text/json": {
                "schema": {
                  "$ref": "#/components/schemas/F1driver"
                }
              }
            }
          }
        }
      }
    },
    "/api/F1driver/{id}": {
      "put": {
        "tags": [
          "F1driver"
        ],
        "parameters": [
          {
            "name": "id",
            "in": "path",
            "required": true,
            "schema": {
              "type": "integer",
              "format": "int32"
            }
          }
        ],
        "requestBody": {
          "content": {
            "application/json": {
              "schema": {
                "$ref": "#/components/schemas/F1driverDTO"
              }
            },
            "text/json": {
              "schema": {
                "$ref": "#/components/schemas/F1driverDTO"
              }
            },
            "application/*+json": {
              "schema": {
                "$ref": "#/components/schemas/F1driverDTO"
              }
            }
          }
        },
        "responses": {
          "200": {
            "description": "OK",
            "content": {
              "text/plain": {
                "schema": {
                  "$ref": "#/components/schemas/F1driver"
                }
              },
              "application/json": {
                "schema": {
                  "$ref": "#/components/schemas/F1driver"
                }
              },
              "text/json": {
                "schema": {
                  "$ref": "#/components/schemas/F1driver"
                }
              }
            }
          }
        }
      },
      "delete": {
        "tags": [
          "F1driver"
        ],
        "parameters": [
          {
            "name": "id",
            "in": "path",
            "required": true,
            "schema": {
              "type": "integer",
              "format": "int32"
            }
          }
        ],
        "responses": {
          "200": {
            "description": "OK"
          }
        }
      }
    },
    "/api/F1driver/CountOfDrivers": {
      "get": {
        "tags": [
          "F1driver"
        ],
        "responses": {
          "200": {
            "description": "OK",
            "content": {
              "text/plain": {
                "schema": {
                  "type": "integer",
                  "format": "int32"
                }
              },
              "application/json": {
                "schema": {
                  "type": "integer",
                  "format": "int32"
                }
              },
              "text/json": {
                "schema": {
                  "type": "integer",
                  "format": "int32"
                }
              }
            }
          }
        }
      }
    },
    "/api/F1driver/Filter_by_Nationality/{nationality}": {
      "get": {
        "tags": [
          "F1driver"
        ],
        "parameters": [
          {
            "name": "nationality",
            "in": "path",
            "required": true,
            "schema": {
              "type": "string"
            }
          }
        ],
        "responses": {
          "200": {
            "description": "OK",
            "content": {
              "text/plain": {
                "schema": {
                  "type": "array",
                  "items": {
                    "$ref": "#/components/schemas/F1driver"
                  }
                }
              },
              "application/json": {
                "schema": {
                  "type": "array",
                  "items": {
                    "$ref": "#/components/schemas/F1driver"
                  }
                }
              },
              "text/json": {
                "schema": {
                  "type": "array",
                  "items": {
                    "$ref": "#/components/schemas/F1driver"
                  }
                }
              }
            }
          }
        }
      }
    },
    "/api/F1team": {
      "get": {
        "tags": [
          "F1team"
        ],
        "responses": {
          "200": {
            "description": "OK",
            "content": {
              "text/plain": {
                "schema": {
                  "type": "array",
                  "items": {
                    "$ref": "#/components/schemas/F1team"
                  }
                }
              },
              "application/json": {
                "schema": {
                  "type": "array",
                  "items": {
                    "$ref": "#/components/schemas/F1team"
                  }
                }
              },
              "text/json": {
                "schema": {
                  "type": "array",
                  "items": {
                    "$ref": "#/components/schemas/F1team"
                  }
                }
              }
            }
          }
        }
      },
      "post": {
        "tags": [
          "F1team"
        ],
        "requestBody": {
          "content": {
            "application/json": {
              "schema": {
                "$ref": "#/components/schemas/F1teamDTO"
              }
            },
            "text/json": {
              "schema": {
                "$ref": "#/components/schemas/F1teamDTO"
              }
            },
            "application/*+json": {
              "schema": {
                "$ref": "#/components/schemas/F1teamDTO"
              }
            }
          }
        },
        "responses": {
          "200": {
            "description": "OK",
            "content": {
              "text/plain": {
                "schema": {
                  "$ref": "#/components/schemas/F1team"
                }
              },
              "application/json": {
                "schema": {
                  "$ref": "#/components/schemas/F1team"
                }
              },
              "text/json": {
                "schema": {
                  "$ref": "#/components/schemas/F1team"
                }
              }
            }
          }
        }
      }
    },
    "/api/F1team/Search_by_TeamId/{id}": {
      "get": {
        "tags": [
          "F1team"
        ],
        "parameters": [
          {
            "name": "id",
            "in": "path",
            "required": true,
            "schema": {
              "type": "integer",
              "format": "int32"
            }
          }
        ],
        "responses": {
          "200": {
            "description": "OK",
            "content": {
              "text/plain": {
                "schema": {
                  "$ref": "#/components/schemas/F1team"
                }
              },
              "application/json": {
                "schema": {
                  "$ref": "#/components/schemas/F1team"
                }
              },
              "text/json": {
                "schema": {
                  "$ref": "#/components/schemas/F1team"
                }
              }
            }
          }
        }
      }
    },
    "/api/F1team/Search_by_TeamName/{name}": {
      "get": {
        "tags": [
          "F1team"
        ],
        "parameters": [
          {
            "name": "name",
            "in": "path",
            "required": true,
            "schema": {
              "type": "string"
            }
          }
        ],
        "responses": {
          "200": {
            "description": "OK",
            "content": {
              "text/plain": {
                "schema": {
                  "$ref": "#/components/schemas/F1team"
                }
              },
              "application/json": {
                "schema": {
                  "$ref": "#/components/schemas/F1team"
                }
              },
              "text/json": {
                "schema": {
                  "$ref": "#/components/schemas/F1team"
                }
              }
            }
          }
        }
      }
    },
    "/api/F1team/{id}": {
      "put": {
        "tags": [
          "F1team"
        ],
        "parameters": [
          {
            "name": "id",
            "in": "path",
            "required": true,
            "schema": {
              "type": "integer",
              "format": "int32"
            }
          }
        ],
        "requestBody": {
          "content": {
            "application/json": {
              "schema": {
                "$ref": "#/components/schemas/F1teamDTO"
              }
            },
            "text/json": {
              "schema": {
                "$ref": "#/components/schemas/F1teamDTO"
              }
            },
            "application/*+json": {
              "schema": {
                "$ref": "#/components/schemas/F1teamDTO"
              }
            }
          }
        },
        "responses": {
          "200": {
            "description": "OK"
          }
        }
      },
      "delete": {
        "tags": [
          "F1team"
        ],
        "parameters": [
          {
            "name": "id",
            "in": "path",
            "required": true,
            "schema": {
              "type": "integer",
              "format": "int32"
            }
          }
        ],
        "responses": {
          "200": {
            "description": "OK"
          }
        }
      }
    },
    "/api/F1team/CountOfTeams": {
      "get": {
        "tags": [
          "F1team"
        ],
        "responses": {
          "200": {
            "description": "OK",
            "content": {
              "text/plain": {
                "schema": {
                  "type": "integer",
                  "format": "int32"
                }
              },
              "application/json": {
                "schema": {
                  "type": "integer",
                  "format": "int32"
                }
              },
              "text/json": {
                "schema": {
                  "type": "integer",
                  "format": "int32"
                }
              }
            }
          }
        }
      }
    },
    "/api/F1team/TeamsFoundedAfter/{year}": {
      "get": {
        "tags": [
          "F1team"
        ],
        "parameters": [
          {
            "name": "year",
            "in": "path",
            "required": true,
            "schema": {
              "type": "integer",
              "format": "int32"
            }
          }
        ],
        "responses": {
          "200": {
            "description": "OK",
            "content": {
              "text/plain": {
                "schema": {
                  "type": "array",
                  "items": {
                    "$ref": "#/components/schemas/F1team"
                  }
                }
              },
              "application/json": {
                "schema": {
                  "type": "array",
                  "items": {
                    "$ref": "#/components/schemas/F1team"
                  }
                }
              },
              "text/json": {
                "schema": {
                  "type": "array",
                  "items": {
                    "$ref": "#/components/schemas/F1team"
                  }
                }
              }
            }
          }
        }
      }
    },
    "/api/Token": {
      "post": {
        "tags": [
          "Token"
        ],
        "requestBody": {
          "content": {
            "application/json": {
              "schema": {
                "$ref": "#/components/schemas/LoginDTO"
              }
            },
            "text/json": {
              "schema": {
                "$ref": "#/components/schemas/LoginDTO"
              }
            },
            "application/*+json": {
              "schema": {
                "$ref": "#/components/schemas/LoginDTO"
              }
            }
          }
        },
        "responses": {
          "200": {
            "description": "OK"
          }
        }
      }
    },
    "/api/Users": {
      "get": {
        "tags": [
          "Users"
        ],
        "responses": {
          "200": {
            "description": "OK",
            "content": {
              "text/plain": {
                "schema": {
                  "type": "array",
                  "items": {
                    "$ref": "#/components/schemas/User"
                  }
                }
              },
              "application/json": {
                "schema": {
                  "type": "array",
                  "items": {
                    "$ref": "#/components/schemas/User"
                  }
                }
              },
              "text/json": {
                "schema": {
                  "type": "array",
                  "items": {
                    "$ref": "#/components/schemas/User"
                  }
                }
              }
            }
          }
        }
      },
      "post": {
        "tags": [
          "Users"
        ],
        "requestBody": {
          "content": {
            "application/json": {
              "schema": {
                "$ref": "#/components/schemas/User"
              }
            },
            "text/json": {
              "schema": {
                "$ref": "#/components/schemas/User"
              }
            },
            "application/*+json": {
              "schema": {
                "$ref": "#/components/schemas/User"
              }
            }
          }
        },
        "responses": {
          "200": {
            "description": "OK",
            "content": {
              "text/plain": {
                "schema": {
                  "$ref": "#/components/schemas/User"
                }
              },
              "application/json": {
                "schema": {
                  "$ref": "#/components/schemas/User"
                }
              },
              "text/json": {
                "schema": {
                  "$ref": "#/components/schemas/User"
                }
              }
            }
          }
        }
      }
    },
    "/api/Users/Filter_by_Role/{role}": {
      "get": {
        "tags": [
          "Users"
        ],
        "parameters": [
          {
            "name": "role",
            "in": "path",
            "required": true,
            "schema": {
              "type": "string"
            }
          }
        ],
        "responses": {
          "200": {
            "description": "OK",
            "content": {
              "text/plain": {
                "schema": {
                  "type": "array",
                  "items": {
                    "$ref": "#/components/schemas/User"
                  }
                }
              },
              "application/json": {
                "schema": {
                  "type": "array",
                  "items": {
                    "$ref": "#/components/schemas/User"
                  }
                }
              },
              "text/json": {
                "schema": {
                  "type": "array",
                  "items": {
                    "$ref": "#/components/schemas/User"
                  }
                }
              }
            }
          }
        }
      }
    },
    "/WeatherForecast": {
      "get": {
        "tags": [
          "WeatherForecast"
        ],
        "operationId": "GetWeatherForecast",
        "responses": {
          "200": {
            "description": "OK",
            "content": {
              "text/plain": {
                "schema": {
                  "type": "array",
                  "items": {
                    "$ref": "#/components/schemas/WeatherForecast"
                  }
                }
              },
              "application/json": {
                "schema": {
                  "type": "array",
                  "items": {
                    "$ref": "#/components/schemas/WeatherForecast"
                  }
                }
              },
              "text/json": {
                "schema": {
                  "type": "array",
                  "items": {
                    "$ref": "#/components/schemas/WeatherForecast"
                  }
                }
              }
            }
          }
        }
      }
    },
    "/api/Worldchampion": {
      "get": {
        "tags": [
          "Worldchampion"
        ],
        "responses": {
          "200": {
            "description": "OK",
            "content": {
              "text/plain": {
                "schema": {
                  "type": "array",
                  "items": {
                    "$ref": "#/components/schemas/WorldChampion"
                  }
                }
              },
              "application/json": {
                "schema": {
                  "type": "array",
                  "items": {
                    "$ref": "#/components/schemas/WorldChampion"
                  }
                }
              },
              "text/json": {
                "schema": {
                  "type": "array",
                  "items": {
                    "$ref": "#/components/schemas/WorldChampion"
                  }
                }
              }
            }
          }
        }
      },
      "post": {
        "tags": [
          "Worldchampion"
        ],
        "requestBody": {
          "content": {
            "application/json": {
              "schema": {
                "$ref": "#/components/schemas/WorldchampionDTO"
              }
            },
            "text/json": {
              "schema": {
                "$ref": "#/components/schemas/WorldchampionDTO"
              }
            },
            "application/*+json": {
              "schema": {
                "$ref": "#/components/schemas/WorldchampionDTO"
              }
            }
          }
        },
        "responses": {
          "200": {
            "description": "OK",
            "content": {
              "text/plain": {
                "schema": {
                  "$ref": "#/components/schemas/WorldChampion"
                }
              },
              "application/json": {
                "schema": {
                  "$ref": "#/components/schemas/WorldChampion"
                }
              },
              "text/json": {
                "schema": {
                  "$ref": "#/components/schemas/WorldChampion"
                }
              }
            }
          }
        }
      }
    },
    "/api/Worldchampion/Search_by_ChampionId/{id}": {
      "get": {
        "tags": [
          "Worldchampion"
        ],
        "parameters": [
          {
            "name": "id",
            "in": "path",
            "required": true,
            "schema": {
              "type": "integer",
              "format": "int32"
            }
          }
        ],
        "responses": {
          "200": {
            "description": "OK",
            "content": {
              "text/plain": {
                "schema": {
                  "$ref": "#/components/schemas/WorldChampion"
                }
              },
              "application/json": {
                "schema": {
                  "$ref": "#/components/schemas/WorldChampion"
                }
              },
              "text/json": {
                "schema": {
                  "$ref": "#/components/schemas/WorldChampion"
                }
              }
            }
          }
        }
      }
    },
    "/api/Worldchampion/Search_by_ChampionName/{name}": {
      "get": {
        "tags": [
          "Worldchampion"
        ],
        "parameters": [
          {
            "name": "name",
            "in": "path",
            "required": true,
            "schema": {
              "type": "string"
            }
          }
        ],
        "responses": {
          "200": {
            "description": "OK",
            "content": {
              "text/plain": {
                "schema": {
                  "$ref": "#/components/schemas/WorldChampion"
                }
              },
              "application/json": {
                "schema": {
                  "$ref": "#/components/schemas/WorldChampion"
                }
              },
              "text/json": {
                "schema": {
                  "$ref": "#/components/schemas/WorldChampion"
                }
              }
            }
          }
        }
      }
    },
    "/api/Worldchampion/{id}": {
      "put": {
        "tags": [
          "Worldchampion"
        ],
        "parameters": [
          {
            "name": "id",
            "in": "path",
            "required": true,
            "schema": {
              "type": "integer",
              "format": "int32"
            }
          }
        ],
        "requestBody": {
          "content": {
            "application/json": {
              "schema": {
                "$ref": "#/components/schemas/WorldchampionDTO"
              }
            },
            "text/json": {
              "schema": {
                "$ref": "#/components/schemas/WorldchampionDTO"
              }
            },
            "application/*+json": {
              "schema": {
                "$ref": "#/components/schemas/WorldchampionDTO"
              }
            }
          }
        },
        "responses": {
          "200": {
            "description": "OK",
            "content": {
              "text/plain": {
                "schema": {
                  "$ref": "#/components/schemas/WorldChampion"
                }
              },
              "application/json": {
                "schema": {
                  "$ref": "#/components/schemas/WorldChampion"
                }
              },
              "text/json": {
                "schema": {
                  "$ref": "#/components/schemas/WorldChampion"
                }
              }
            }
          }
        }
      },
      "delete": {
        "tags": [
          "Worldchampion"
        ],
        "parameters": [
          {
            "name": "id",
            "in": "path",
            "required": true,
            "schema": {
              "type": "integer",
              "format": "int32"
            }
          }
        ],
        "responses": {
          "200": {
            "description": "OK"
          }
        }
      }
    },
    "/api/Worldchampion/CountOfChampions": {
      "get": {
        "tags": [
          "Worldchampion"
        ],
        "responses": {
          "200": {
            "description": "OK",
            "content": {
              "text/plain": {
                "schema": {
                  "type": "integer",
                  "format": "int32"
                }
              },
              "application/json": {
                "schema": {
                  "type": "integer",
                  "format": "int32"
                }
              },
              "text/json": {
                "schema": {
                  "type": "integer",
                  "format": "int32"
                }
              }
            }
          }
        }
      }
    },
    "/api/Worldchampion/Filter_by_Points/{min}/{max}": {
      "get": {
        "tags": [
          "Worldchampion"
        ],
        "parameters": [
          {
            "name": "min",
            "in": "path",
            "required": true,
            "schema": {
              "type": "integer",
              "format": "int32"
            }
          },
          {
            "name": "max",
            "in": "path",
            "required": true,
            "schema": {
              "type": "integer",
              "format": "int32"
            }
          }
        ],
        "responses": {
          "200": {
            "description": "OK",
            "content": {
              "text/plain": {
                "schema": {
                  "type": "array",
                  "items": {
                    "$ref": "#/components/schemas/WorldChampion"
                  }
                }
              },
              "application/json": {
                "schema": {
                  "type": "array",
                  "items": {
                    "$ref": "#/components/schemas/WorldChampion"
                  }
                }
              },
              "text/json": {
                "schema": {
                  "type": "array",
                  "items": {
                    "$ref": "#/components/schemas/WorldChampion"
                  }
                }
              }
            }
          }
        }
      }
    }
  },
  "components": {
    "schemas": {
      "F1driver": {
        "type": "object",
        "properties": {
          "driverNumber": {
            "type": "integer",
            "format": "int32"
          },
          "driverName": {
            "type": "string",
            "nullable": true
          },
          "nationality": {
            "type": "string",
            "nullable": true
          },
          "teamId": {
            "type": "integer",
            "format": "int32",
            "nullable": true
          },
          "teamName": {
            "type": "string",
            "nullable": true
          },
          "team": {
            "$ref": "#/components/schemas/F1team"
          },
          "user": {
            "$ref": "#/components/schemas/User"
          },
          "worldChampions": {
            "type": "array",
            "items": {
              "$ref": "#/components/schemas/WorldChampion"
            },
            "nullable": true
          }
        },
        "additionalProperties": false
      },
      "F1driverDTO": {
        "type": "object",
        "properties": {
          "driverNumber": {
            "type": "integer",
            "format": "int32"
          },
          "driverName": {
            "type": "string",
            "nullable": true
          },
          "nationality": {
            "type": "string",
            "nullable": true
          },
          "teamId": {
            "type": "integer",
            "format": "int32",
            "nullable": true
          },
          "teamName": {
            "type": "string",
            "nullable": true
          }
        },
        "additionalProperties": false
      },
      "F1team": {
        "type": "object",
        "properties": {
          "teamId": {
            "type": "integer",
            "format": "int32"
          },
          "teamName": {
            "type": "string",
            "nullable": true
          },
          "baseCountry": {
            "type": "string",
            "nullable": true
          },
          "teamPrincipal": {
            "type": "string",
            "nullable": true
          },
          "foundedYear": {
            "type": "integer",
            "format": "int32",
            "nullable": true
          },
          "f1drivers": {
            "type": "array",
            "items": {
              "$ref": "#/components/schemas/F1driver"
            },
            "nullable": true
          }
        },
        "additionalProperties": false
      },
      "F1teamDTO": {
        "type": "object",
        "properties": {
          "teamId": {
            "type": "integer",
            "format": "int32"
          },
          "teamName": {
            "type": "string",
            "nullable": true
          },
          "baseCountry": {
            "type": "string",
            "nullable": true
          },
          "teamPrincipal": {
            "type": "string",
            "nullable": true
          },
          "foundedYear": {
            "type": "integer",
            "format": "int32",
            "nullable": true
          }
        },
        "additionalProperties": false
      },
      "LoginDTO": {
        "type": "object",
        "properties": {
          "userName": {
            "type": "string",
            "nullable": true
          },
          "password": {
            "type": "string",
            "nullable": true
          }
        },
        "additionalProperties": false
      },
      "User": {
        "type": "object",
        "properties": {
          "userId": {
            "type": "integer",
            "format": "int32"
          },
          "userName": {
            "type": "string",
            "nullable": true
          },
          "password": {
            "type": "string",
            "nullable": true
          },
          "role": {
            "type": "string",
            "nullable": true
          },
          "userNavigation": {
            "$ref": "#/components/schemas/F1driver"
          }
        },
        "additionalProperties": false
      },
      "WeatherForecast": {
        "type": "object",
        "properties": {
          "date": {
            "type": "string",
            "format": "date"
          },
          "temperatureC": {
            "type": "integer",
            "format": "int32"
          },
          "temperatureF": {
            "type": "integer",
            "format": "int32",
            "readOnly": true
          },
          "summary": {
            "type": "string",
            "nullable": true
          }
        },
        "additionalProperties": false
      },
      "WorldChampion": {
        "type": "object",
        "properties": {
          "championId": {
            "type": "integer",
            "format": "int32"
          },
          "driverNumber": {
            "type": "integer",
            "format": "int32",
            "nullable": true
          },
          "winningYear": {
            "type": "integer",
            "format": "int32",
            "nullable": true
          },
          "driverName": {
            "type": "string",
            "nullable": true
          },
          "teamName": {
            "type": "string",
            "nullable": true
          },
          "points": {
            "type": "integer",
            "format": "int32",
            "nullable": true
          },
          "driverNumberNavigation": {
            "$ref": "#/components/schemas/F1driver"
          }
        },
        "additionalProperties": false
      },
      "WorldchampionDTO": {
        "type": "object",
        "properties": {
          "championId": {
            "type": "integer",
            "format": "int32"
          },
          "driverNumber": {
            "type": "integer",
            "format": "int32",
            "nullable": true
          },
          "winningYear": {
            "type": "integer",
            "format": "int32",
            "nullable": true
          },
          "driverName": {
            "type": "string",
            "nullable": true
          },
          "teamName": {
            "type": "string",
            "nullable": true
          },
          "points": {
            "type": "integer",
            "format": "int32",
            "nullable": true
          }
        },
        "additionalProperties": false
      }
    },
    "securitySchemes": {
      "Bearer": {
        "type": "http",
        "description": "JWT Authorization header using the Bearer scheme.",
        "scheme": "Bearer",
        "bearerFormat": "JWT"
      }
    }
  },
  "security": [
    {
      "Bearer": [ ]
    }
  ]
}